pyautomationml/__init__.py
pyautomationml/pyautomationml.py
pyautomationml-1.1.3.dist-info/LICENSE
pyautomationml-1.1.3.dist-info/METADATA
pyautomationml-1.1.3.dist-info/WHEEL
pyautomationml-1.1.3.dist-info/top_level.txt
pyautomationml-1.1.3.dist-info/RECORD
