Metadata-Version: 2.1
Name: pyautomationml
Version: 1.1.3
Summary: Library for processing AutomationML files in python
Home-page: https://github.com/CIIRC-ISI/PyAML
Author: CIIRC ISI Microteam
Author-email: doudape1@fel.cvut.cz
License: BSD
Platform: UNKNOWN
Classifier: License :: OSI Approved :: BSD License
Classifier: Programming Language :: Python :: 3
Classifier: Programming Language :: Python :: 3.8
Requires-Dist: lxml
